{
"binXLen": 12,
"binYLen": 12,
"gameType": "bp",
"items": [
{"xLen": 4, "yLen": 6, "color": "hsl(148,90%,60%)"},
{"xLen": 2, "yLen": 11, "color": "hsl(231,90%,60%)"},
{"xLen": 2, "yLen": 11, "color": "hsl(52,90%,60%)"},
{"xLen": 10, "yLen": 1, "color": "hsl(172,90%,60%)"},
{"xLen": 2, "yLen": 5, "color": "hsl(206,90%,60%)"},
{"xLen": 1, "yLen": 9, "color": "hsl(350,90%,60%)"},
{"xLen": 2, "yLen": 4, "color": "hsl(346,90%,60%)"},
{"xLen": 2, "yLen": 4, "color": "hsl(7,90%,60%)"},
{"xLen": 1, "yLen": 7, "color": "hsl(269,90%,60%)"},
{"xLen": 3, "yLen": 2, "color": "hsl(193,90%,60%)"},
{"xLen": 3, "yLen": 2, "color": "hsl(139,90%,60%)"},
{"xLen": 4, "yLen": 1, "color": "hsl(195,90%,60%)"},
{"xLen": 2, "yLen": 2, "color": "hsl(268,90%,60%)"}
],
"startPos": [
[0, 0, 0],
[0, 8, 0],
[0, 10, 0],
[0, 2, 11],
[0, 5, 4],
[0, 7, 0],
[0, 0, 8],
[0, 5, 0],
[0, 4, 0],
[0, 2, 8],
[0, 1, 6],
[0, 2, 10],
[0, 6, 9]
],
"solution": [
[0, 1, 4],
[0, 5, 0],
[0, 7, 0],
[0, 0, 11],
[0, 10, 6],
[0, 9, 2],
[0, 0, 0],
[0, 10, 2],
[0, 0, 4],
[0, 2, 0],
[0, 9, 0],
[0, 1, 10],
[0, 3, 2]
]
}